vmigration_helper/__init__.py
vmigration_helper/apps.py
vmigration_helper/helpers/__init__.py
vmigration_helper/helpers/command.py
vmigration_helper/helpers/migration_records.py
vmigration_helper/management/__init__.py
vmigration_helper/management/commands/__init__.py
vmigration_helper/management/commands/migration_current_id.py
vmigration_helper/management/commands/migration_delete.py
vmigration_helper/management/commands/migration_records.py
vmigration_helper/management/commands/migration_rollback.py
vmigration_helper/migrations/__init__.py
vmigration_helper-1.1.0.dist-info/LICENSE
vmigration_helper-1.1.0.dist-info/METADATA
vmigration_helper-1.1.0.dist-info/WHEEL
vmigration_helper-1.1.0.dist-info/RECORD
