Metadata-Version: 2.1
Name: vmigration-helper
Version: 1.1.0
Summary: Van's Django Migration Helper
Home-page: https://github.com/bluedenim/vmigration-helper
Keywords: django,migration,rollback
Author: bluedenim
Author-email: vancly@hotmail.com
Requires-Python: >=3.8,<4.0
Classifier: Programming Language :: Python :: 3
Classifier: Programming Language :: Python :: 3.8
Classifier: Programming Language :: Python :: 3.9
Classifier: Programming Language :: Python :: 3.10
Classifier: Programming Language :: Python :: 3.11
Classifier: Programming Language :: Python :: 3.12
Classifier: Programming Language :: Python :: 3.13
Requires-Dist: Django (>=1.11.17,<5)
